{
  "docId": 3993959,
  "nodeType": "TAXONOMY",
  "primaryParent": null,
  "primaryParentWeight": 1.0,
  "document": {
    "key": null,
    "revisionKey": null,
    "authorKey": null,
    "ownerKey": null,
    "url": "https://www.lifewire.com/yoga-3993959",
    "rootUrl": "https://www.lifewire.com/yoga-3993959",
    "templateType": "TAXONOMY",
    "documentState": null,
    "circulationsettings": null,
    "dates": null,
    "medicalBoardApproved": null,
    "editingAuthorKey": null,
    "noIndex": null,
    "title": "Yoga - Articles, Advice, and More",
    "socialTitle": null,
    "keywords": {
      "limit": null,
      "offset": null,
      "totalSize": 0,
      "list": [],
      "empty": true
    },
    "metaDescription": null,
    "description": "Learn about yoga practices that'll get you relaxed and recentered, whether you're a beginner or a pro.",
    "heading": "Yoga",
    "paging": null,
    "categoryPromos": {
      "limit": null,
      "offset": null,
      "totalSize": 0,
      "list": [],
      "empty": true
    },
    "category": null,
    "author": {
      "id": null,
      "type": null,
      "status": null,
      "siteDirName": null,
      "taxonomyInfo": null,
      "displayName": null,
      "displayNamePossessive": null,
      "contributingWriter": false,
      "language": null,
      "promotionDate": null,
      "liveDate": null,
      "terminationDate": null,
      "numberOfExperts": null,
      "socialPresence": [],
      "socialPresenceMap": {},
      "bioUrl": null,
      "imageUrl": null
    },
    "stamp": {
      "url": "https://www.lifewire.com/yoga-3993959",
      "stampValue": "vw_yoga",
      "adValue": "pidvw_yoga",
      "audit": {
        "clientId": null,
        "lastModified": null
      }
    },
    "userReview": null,
    "summary": {
      "title": "Yoga - Articles, Advice, and More",
      "socialTitle": "Yoga - Articles, Advice, and More",
      "heading": "Yoga",
      "description": "You might have a favorite type of yoga and not even know it. Learn about hatha, vinyasa, and more yoga practices that'll get you relaxed and recentered, whether you're a beginner or a pro.",
      "image": {
        "url": null,
        "caption": null,
        "owner": null,
        "alt": null,
        "width": 1920,
        "height": 1080,
        "id": null,
        "fileName": null,
        "objectPath": null,
        "objectId": "Illo_Yoga-56f17dfbcb64651622d97c06.png",
        "empty": true,
        "notEmpty": false
      }
    },
    "metaData": null,
    "shortHeading": "Yoga",
    "viewType": null,
    "thumbImage": {
      "url": null,
      "caption": null,
      "owner": null,
      "alt": null,
      "width": 1080,
      "height": 1080,
      "id": null,
      "fileName": null,
      "objectPath": null,
      "objectId": "IlloDot_Yoga-56f1950bcb64651bb12061c2.png",
      "empty": true,
      "notEmpty": false
    },
    "contentLength": 0,
    "characterCount": 0,
    "review": false,
    "inNetworkCategoryLinks": [],
    "offNetworkCategoryLinks": [],
    "images": [],
    "subheading": null,
    "primaryImage": {
      "url": null,
      "caption": null,
      "owner": null,
      "alt": null,
      "width": 1920,
      "height": 1080,
      "id": null,
      "fileName": null,
      "objectPath": null,
      "objectId": "Illo_Yoga-56f17dfbcb64651622d97c06.png",
      "empty": true,
      "notEmpty": false
    },
    "bestTitle": "Yoga",
    "docId": 3993959
  },
  "children": {
    "limit": 16,
    "offset": 0,
    "totalSize": 16,
    "list": [
      {
        "docId": 3993912,
        "nodeType": "TAXONOMY",
        "primaryParent": null,
        "primaryParentWeight": 1.0,
        "document": {
          "key": null,
          "revisionKey": null,
          "authorKey": null,
          "ownerKey": null,
          "url": "https://www.lifewire.com/yoga-popular-types-3993912",
          "rootUrl": "https://www.lifewire.com/yoga-popular-types-3993912",
          "templateType": "TAXONOMY",
          "documentState": null,
          "circulationsettings": null,
          "dates": null,
          "medicalBoardApproved": null,
          "editingAuthorKey": null,
          "noIndex": null,
          "title": "Popular Yoga Types Explained",
          "socialTitle": null,
          "keywords": {
            "limit": null,
            "offset": null,
            "totalSize": 0,
            "list": [],
            "empty": true
          },
          "metaDescription": null,
          "description": "Almost all types of yoga share the same foundation of poses, but there are differences. Learn about the varying approaches to different yoga styles.",
          "heading": "Popular Yoga Types Explained",
          "paging": null,
          "categoryPromos": {
            "limit": null,
            "offset": null,
            "totalSize": 0,
            "list": [],
            "empty": true
          },
          "category": null,
          "author": {
            "id": null,
            "type": null,
            "status": null,
            "siteDirName": null,
            "taxonomyInfo": null,
            "displayName": null,
            "displayNamePossessive": null,
            "contributingWriter": false,
            "language": null,
            "promotionDate": null,
            "liveDate": null,
            "terminationDate": null,
            "numberOfExperts": null,
            "socialPresence": [],
            "socialPresenceMap": {},
            "bioUrl": null,
            "imageUrl": null
          },
          "stamp": {
            "url": "https://www.lifewire.com/yoga-popular-types-3993912",
            "stampValue": "vw_yoga-popular-types",
            "adValue": "pidvw_yoga-popular-types",
            "audit": {
              "clientId": null,
              "lastModified": null
            }
          },
          "userReview": null,
          "summary": {
            "title": "Popular Yoga Types Explained",
            "socialTitle": "Popular Yoga Types Explained",
            "heading": "Popular Yoga Types Explained",
            "description": "Almost all types of yoga share the same foundation of poses, but there are differences. Learn about the varying approaches to different yoga styles.",
            "image": {
              "url": null,
              "caption": null,
              "owner": null,
              "alt": null,
              "width": null,
              "height": null,
              "id": null,
              "fileName": null,
              "objectPath": null,
              "objectId": null,
              "empty": true,
              "notEmpty": false
            }
          },
          "metaData": null,
          "shortHeading": "Popular Types",
          "viewType": null,
          "thumbImage": null,
          "contentLength": 0,
          "characterCount": 0,
          "review": false,
          "inNetworkCategoryLinks": [],
          "offNetworkCategoryLinks": [],
          "images": [],
          "subheading": null,
          "primaryImage": {
            "url": null,
            "caption": null,
            "owner": null,
            "alt": null,
            "width": null,
            "height": null,
            "id": null,
            "fileName": null,
            "objectPath": null,
            "objectId": null,
            "empty": true,
            "notEmpty": false
          },
          "bestTitle": "Popular Yoga Types Explained",
          "docId": 3993912
        },
        "children": {
          "limit": null,
          "offset": null,
          "totalSize": 0,
          "list": [],
          "empty": true
        },
        "descendantDocuments": []
      },
      {
        "docId": 3993913,
        "nodeType": "TAXONOMY",
        "primaryParent": null,
        "primaryParentWeight": 0.049155,
        "document": {
          "key": null,
          "revisionKey": null,
          "authorKey": null,
          "ownerKey": null,
          "url": "https://www.lifewire.com/yoga-sequences-for-home-practice-3993913",
          "rootUrl": "https://www.lifewire.com/yoga-sequences-for-home-practice-3993913",
          "templateType": "TAXONOMY",
          "documentState": null,
          "circulationsettings": null,
          "dates": null,
          "medicalBoardApproved": null,
          "editingAuthorKey": null,
          "noIndex": null,
          "title": "Yoga Sequences for Home Practice",
          "socialTitle": null,
          "keywords": {
            "limit": null,
            "offset": null,
            "totalSize": 0,
            "list": [],
            "empty": true
          },
          "metaDescription": null,
          "description": "Practice yoga whenever and wherever you want. These yoga sequences and poses suit a range of skill levels and are perfect for an at-home workout.",
          "heading": "Yoga Sequences for Home Practice",
          "paging": null,
          "categoryPromos": {
            "limit": null,
            "offset": null,
            "totalSize": 0,
            "list": [],
            "empty": true
          },
          "category": null,
          "author": {
            "id": null,
            "type": null,
            "status": null,
            "siteDirName": null,
            "taxonomyInfo": null,
            "displayName": null,
            "displayNamePossessive": null,
            "contributingWriter": false,
            "language": null,
            "promotionDate": null,
            "liveDate": null,
            "terminationDate": null,
            "numberOfExperts": null,
            "socialPresence": [],
            "socialPresenceMap": {},
            "bioUrl": null,
            "imageUrl": null
          },
          "stamp": {
            "url": "https://www.lifewire.com/yoga-sequences-for-home-practice-3993913",
            "stampValue": "vw_yoga-sequences-for-home-practice",
            "adValue": "pidvw_yoga-sequences-for-home-practice",
            "audit": {
              "clientId": null,
              "lastModified": null
            }
          },
          "userReview": null,
          "summary": {
            "title": "Yoga Sequences for Home Practice",
            "socialTitle": "Yoga Sequences for Home Practice",
            "heading": "Yoga Sequences for Home Practice",
            "description": "Practice yoga whenever and wherever you want. These yoga sequences and poses suit a range of skill levels and are perfect for an at-home workout.",
            "image": {
              "url": null,
              "caption": null,
              "owner": null,
              "alt": null,
              "width": null,
              "height": null,
              "id": null,
              "fileName": null,
              "objectPath": null,
              "objectId": null,
              "empty": true,
              "notEmpty": false
            }
          },
          "metaData": null,
          "shortHeading": "Sequences for Home Practice",
          "viewType": null,
          "thumbImage": null,
          "contentLength": 0,
          "characterCount": 0,
          "review": false,
          "inNetworkCategoryLinks": [],
          "offNetworkCategoryLinks": [],
          "images": [],
          "subheading": null,
          "primaryImage": {
            "url": null,
            "caption": null,
            "owner": null,
            "alt": null,
            "width": null,
            "height": null,
            "id": null,
            "fileName": null,
            "objectPath": null,
            "objectId": null,
            "empty": true,
            "notEmpty": false
          },
          "bestTitle": "Yoga Sequences for Home Practice",
          "docId": 3993913
        },
        "children": {
          "limit": null,
          "offset": null,
          "totalSize": 0,
          "list": [],
          "empty": true
        },
        "descendantDocuments": []
      },
      {
        "docId": 3993914,
        "nodeType": "TAXONOMY",
        "primaryParent": null,
        "primaryParentWeight": 0.048775,
        "document": {
          "key": null,
          "revisionKey": null,
          "authorKey": null,
          "ownerKey": null,
          "url": "https://www.lifewire.com/beginner-yoga-3993914",
          "rootUrl": "https://www.lifewire.com/beginner-yoga-3993914",
          "templateType": "TAXONOMY",
          "documentState": null,
          "circulationsettings": null,
          "dates": null,
          "medicalBoardApproved": null,
          "editingAuthorKey": null,
          "noIndex": null,
          "title": "Yoga Practice for Beginners",
          "socialTitle": null,
          "keywords": {
            "limit": null,
            "offset": null,
            "totalSize": 0,
            "list": [],
            "empty": true
          },
          "metaDescription": null,
          "description": "If you’re new to yoga, this beginner’s yoga guide will teach you basic poses and stretches, what to expect in your first class and proper etiquette.",
          "heading": "Yoga Practice for Beginners",
          "paging": null,
          "categoryPromos": {
            "limit": null,
            "offset": null,
            "totalSize": 0,
            "list": [],
            "empty": true
          },
          "category": null,
          "author": {
            "id": null,
            "type": null,
            "status": null,
            "siteDirName": null,
            "taxonomyInfo": null,
            "displayName": null,
            "displayNamePossessive": null,
            "contributingWriter": false,
            "language": null,
            "promotionDate": null,
            "liveDate": null,
            "terminationDate": null,
            "numberOfExperts": null,
            "socialPresence": [],
            "socialPresenceMap": {},
            "bioUrl": null,
            "imageUrl": null
          },
          "stamp": {
            "url": "https://www.lifewire.com/beginner-yoga-3993914",
            "stampValue": "vw_beginner-yoga",
            "adValue": "pidvw_beginner-yoga",
            "audit": {
              "clientId": null,
              "lastModified": null
            }
          },
          "userReview": null,
          "summary": {
            "title": "Yoga Practice for Beginners",
            "socialTitle": "Yoga Practice for Beginners",
            "heading": "Yoga Practice for Beginners",
            "description": "If you’re new to yoga, this beginner’s yoga guide will teach you basic poses and stretches, what to expect in your first class and proper etiquette.",
            "image": {
              "url": null,
              "caption": null,
              "owner": null,
              "alt": null,
              "width": null,
              "height": null,
              "id": null,
              "fileName": null,
              "objectPath": null,
              "objectId": null,
              "empty": true,
              "notEmpty": false
            }
          },
          "metaData": null,
          "shortHeading": "Beginners",
          "viewType": null,
          "thumbImage": null,
          "contentLength": 0,
          "characterCount": 0,
          "review": false,
          "inNetworkCategoryLinks": [],
          "offNetworkCategoryLinks": [],
          "images": [],
          "subheading": null,
          "primaryImage": {
            "url": null,
            "caption": null,
            "owner": null,
            "alt": null,
            "width": null,
            "height": null,
            "id": null,
            "fileName": null,
            "objectPath": null,
            "objectId": null,
            "empty": true,
            "notEmpty": false
          },
          "bestTitle": "Yoga Practice for Beginners",
          "docId": 3993914
        },
        "children": {
          "limit": null,
          "offset": null,
          "totalSize": 0,
          "list": [],
          "empty": true
        },
        "descendantDocuments": []
      },
      {
        "docId": 3993911,
        "nodeType": "TAXONOMY",
        "primaryParent": null,
        "primaryParentWeight": 0.048485,
        "document": {
          "key": null,
          "revisionKey": null,
          "authorKey": null,
          "ownerKey": null,
          "url": "https://www.lifewire.com/yoga-poses-3993911",
          "rootUrl": "https://www.lifewire.com/yoga-poses-3993911",
          "templateType": "TAXONOMY",
          "documentState": null,
          "circulationsettings": null,
          "dates": null,
          "medicalBoardApproved": null,
          "editingAuthorKey": null,
          "noIndex": null,
          "title": "An Index of Yoga Poses and Sequences",
          "socialTitle": null,
          "keywords": {
            "limit": null,
            "offset": null,
            "totalSize": 0,
            "list": [],
            "empty": true
          },
          "metaDescription": null,
          "description": "These simple explanations and illustrated sequences will teach you how to master yoga poses, from the most basic to the most advanced.",
          "heading": "An Index of Yoga Poses and Sequences",
          "paging": null,
          "categoryPromos": {
            "limit": null,
            "offset": null,
            "totalSize": 0,
            "list": [],
            "empty": true
          },
          "category": null,
          "author": {
            "id": null,
            "type": null,
            "status": null,
            "siteDirName": null,
            "taxonomyInfo": null,
            "displayName": null,
            "displayNamePossessive": null,
            "contributingWriter": false,
            "language": null,
            "promotionDate": null,
            "liveDate": null,
            "terminationDate": null,
            "numberOfExperts": null,
            "socialPresence": [],
            "socialPresenceMap": {},
            "bioUrl": null,
            "imageUrl": null
          },
          "stamp": {
            "url": "https://www.lifewire.com/yoga-poses-3993911",
            "stampValue": "vw_yoga-poses",
            "adValue": "pidvw_yoga-poses",
            "audit": {
              "clientId": null,
              "lastModified": null
            }
          },
          "userReview": null,
          "summary": {
            "title": "An Index of Yoga Poses and Sequences",
            "socialTitle": "An Index of Yoga Poses and Sequences",
            "heading": "An Index of Yoga Poses and Sequences",
            "description": "These simple explanations and illustrated sequences will teach you how to master yoga poses, from the most basic to the most advanced.",
            "image": {
              "url": null,
              "caption": null,
              "owner": null,
              "alt": null,
              "width": null,
              "height": null,
              "id": null,
              "fileName": null,
              "objectPath": null,
              "objectId": null,
              "empty": true,
              "notEmpty": false
            }
          },
          "metaData": null,
          "shortHeading": "Poses",
          "viewType": null,
          "thumbImage": null,
          "contentLength": 0,
          "characterCount": 0,
          "review": false,
          "inNetworkCategoryLinks": [],
          "offNetworkCategoryLinks": [],
          "images": [],
          "subheading": null,
          "primaryImage": {
            "url": null,
            "caption": null,
            "owner": null,
            "alt": null,
            "width": null,
            "height": null,
            "id": null,
            "fileName": null,
            "objectPath": null,
            "objectId": null,
            "empty": true,
            "notEmpty": false
          },
          "bestTitle": "An Index of Yoga Poses and Sequences",
          "docId": 3993911
        },
        "children": {
          "limit": null,
          "offset": null,
          "totalSize": 0,
          "list": [],
          "empty": true
        },
        "descendantDocuments": []
      },
      {
        "docId": 3993915,
        "nodeType": "TAXONOMY",
        "primaryParent": null,
        "primaryParentWeight": 0.04814,
        "document": {
          "key": null,
          "revisionKey": null,
          "authorKey": null,
          "ownerKey": null,
          "url": "https://www.lifewire.com/yoga-clothing-and-equipment-3993915",
          "rootUrl": "https://www.lifewire.com/yoga-clothing-and-equipment-3993915",
          "templateType": "TAXONOMY",
          "documentState": null,
          "circulationsettings": null,
          "dates": null,
          "medicalBoardApproved": null,
          "editingAuthorKey": null,
          "noIndex": null,
          "title": "Yoga Clothing and Gear Recommendations",
          "socialTitle": null,
          "keywords": {
            "limit": null,
            "offset": null,
            "totalSize": 0,
            "list": [],
            "empty": true
          },
          "metaDescription": null,
          "description": "When you look good, you feel good. This guide includes details about the best yoga mats, bags, props, equipment, as well as yoga clothes reviews.",
          "heading": "Yoga Clothing and Gear Recommendations",
          "paging": null,
          "categoryPromos": {
            "limit": null,
            "offset": null,
            "totalSize": 0,
            "list": [],
            "empty": true
          },
          "category": null,
          "author": {
            "id": null,
            "type": null,
            "status": null,
            "siteDirName": null,
            "taxonomyInfo": null,
            "displayName": null,
            "displayNamePossessive": null,
            "contributingWriter": false,
            "language": null,
            "promotionDate": null,
            "liveDate": null,
            "terminationDate": null,
            "numberOfExperts": null,
            "socialPresence": [],
            "socialPresenceMap": {},
            "bioUrl": null,
            "imageUrl": null
          },
          "stamp": {
            "url": "https://www.lifewire.com/yoga-clothing-and-equipment-3993915",
            "stampValue": "vw_yoga-clothing-and-equipment",
            "adValue": "pidvw_yoga-clothing-and-equipment",
            "audit": {
              "clientId": null,
              "lastModified": null
            }
          },
          "userReview": null,
          "summary": {
            "title": "Yoga Clothing and Gear Recommendations",
            "socialTitle": "Yoga Clothing and Gear Recommendations",
            "heading": "Yoga Clothing and Gear Recommendations",
            "description": "When you look good, you feel good. This guide includes details about the best yoga mats, bags, props, equipment, as well as yoga clothes reviews.",
            "image": {
              "url": null,
              "caption": null,
              "owner": null,
              "alt": null,
              "width": null,
              "height": null,
              "id": null,
              "fileName": null,
              "objectPath": null,
              "objectId": null,
              "empty": true,
              "notEmpty": false
            }
          },
          "metaData": null,
          "shortHeading": "Clothing and Equipment",
          "viewType": null,
          "thumbImage": null,
          "contentLength": 0,
          "characterCount": 0,
          "review": false,
          "inNetworkCategoryLinks": [],
          "offNetworkCategoryLinks": [],
          "images": [],
          "subheading": null,
          "primaryImage": {
            "url": null,
            "caption": null,
            "owner": null,
            "alt": null,
            "width": null,
            "height": null,
            "id": null,
            "fileName": null,
            "objectPath": null,
            "objectId": null,
            "empty": true,
            "notEmpty": false
          },
          "bestTitle": "Yoga Clothing and Gear Recommendations",
          "docId": 3993915
        },
        "children": {
          "limit": null,
          "offset": null,
          "totalSize": 0,
          "list": [],
          "empty": true
        },
        "descendantDocuments": []
      },
      {
        "docId": 3993919,
        "nodeType": "TAXONOMY",
        "primaryParent": null,
        "primaryParentWeight": 0.04728,
        "document": {
          "key": null,
          "revisionKey": null,
          "authorKey": null,
          "ownerKey": null,
          "url": "https://www.lifewire.com/yoga-power-3993919",
          "rootUrl": "https://www.lifewire.com/yoga-power-3993919",
          "templateType": "TAXONOMY",
          "documentState": null,
          "circulationsettings": null,
          "dates": null,
          "medicalBoardApproved": null,
          "editingAuthorKey": null,
          "noIndex": null,
          "title": "Approaches to Power Yoga",
          "socialTitle": null,
          "keywords": {
            "limit": null,
            "offset": null,
            "totalSize": 0,
            "list": [],
            "empty": true
          },
          "metaDescription": null,
          "description": "There is yoga and there is power yoga. What's the difference? Explore this strenuous, workout-style of yoga and find out if it's right for you.",
          "heading": "Approaches to Power Yoga",
          "paging": null,
          "categoryPromos": {
            "limit": null,
            "offset": null,
            "totalSize": 0,
            "list": [],
            "empty": true
          },
          "category": null,
          "author": {
            "id": null,
            "type": null,
            "status": null,
            "siteDirName": null,
            "taxonomyInfo": null,
            "displayName": null,
            "displayNamePossessive": null,
            "contributingWriter": false,
            "language": null,
            "promotionDate": null,
            "liveDate": null,
            "terminationDate": null,
            "numberOfExperts": null,
            "socialPresence": [],
            "socialPresenceMap": {},
            "bioUrl": null,
            "imageUrl": null
          },
          "stamp": {
            "url": "https://www.lifewire.com/yoga-power-3993919",
            "stampValue": "vw_yoga-power",
            "adValue": "pidvw_yoga-power",
            "audit": {
              "clientId": null,
              "lastModified": null
            }
          },
          "userReview": null,
          "summary": {
            "title": "Approaches to Power Yoga",
            "socialTitle": "Approaches to Power Yoga",
            "heading": "Approaches to Power Yoga",
            "description": "There is yoga and there is power yoga. What's the difference? Explore this strenuous, workout-style of yoga and find out if it's right for you.",
            "image": {
              "url": null,
              "caption": null,
              "owner": null,
              "alt": null,
              "width": null,
              "height": null,
              "id": null,
              "fileName": null,
              "objectPath": null,
              "objectId": null,
              "empty": true,
              "notEmpty": false
            }
          },
          "metaData": null,
          "shortHeading": "Power Yoga",
          "viewType": null,
          "thumbImage": null,
          "contentLength": 0,
          "characterCount": 0,
          "review": false,
          "inNetworkCategoryLinks": [],
          "offNetworkCategoryLinks": [],
          "images": [],
          "subheading": null,
          "primaryImage": {
            "url": null,
            "caption": null,
            "owner": null,
            "alt": null,
            "width": null,
            "height": null,
            "id": null,
            "fileName": null,
            "objectPath": null,
            "objectId": null,
            "empty": true,
            "notEmpty": false
          },
          "bestTitle": "Approaches to Power Yoga",
          "docId": 3993919
        },
        "children": {
          "limit": null,
          "offset": null,
          "totalSize": 0,
          "list": [],
          "empty": true
        },
        "descendantDocuments": []
      },
      {
        "docId": 3993918,
        "nodeType": "TAXONOMY",
        "primaryParent": null,
        "primaryParentWeight": 0.04724,
        "document": {
          "key": null,
          "revisionKey": null,
          "authorKey": null,
          "ownerKey": null,
          "url": "https://www.lifewire.com/yoga-and-your-tech-3993918",
          "rootUrl": "https://www.lifewire.com/yoga-and-your-tech-3993918",
          "templateType": "TAXONOMY",
          "documentState": null,
          "circulationsettings": null,
          "dates": null,
          "medicalBoardApproved": null,
          "editingAuthorKey": null,
          "noIndex": null,
          "title": "Understanding Yoga and Your Tech",
          "socialTitle": null,
          "keywords": {
            "limit": null,
            "offset": null,
            "totalSize": 0,
            "list": [],
            "empty": true
          },
          "metaDescription": null,
          "description": "Yoga is a wonderful alternative treatment for many injuries and medical conditions. Learn the many yoga therapy benefits, including pain and stress relief.",
          "heading": "Understanding Yoga and Your Tech",
          "paging": null,
          "categoryPromos": {
            "limit": null,
            "offset": null,
            "totalSize": 0,
            "list": [],
            "empty": true
          },
          "category": null,
          "author": {
            "id": null,
            "type": null,
            "status": null,
            "siteDirName": null,
            "taxonomyInfo": null,
            "displayName": null,
            "displayNamePossessive": null,
            "contributingWriter": false,
            "language": null,
            "promotionDate": null,
            "liveDate": null,
            "terminationDate": null,
            "numberOfExperts": null,
            "socialPresence": [],
            "socialPresenceMap": {},
            "bioUrl": null,
            "imageUrl": null
          },
          "stamp": {
            "url": "https://www.lifewire.com/yoga-and-your-tech-3993918",
            "stampValue": "vw_yoga-and-your-tech",
            "adValue": "pidvw_yoga-and-your-tech",
            "audit": {
              "clientId": null,
              "lastModified": null
            }
          },
          "userReview": null,
          "summary": {
            "title": "Understanding Yoga and Your Tech",
            "socialTitle": "Understanding Yoga and Your Tech",
            "heading": "Understanding Yoga and Your Tech",
            "description": "Yoga is a wonderful alternative treatment for many injuries and medical conditions. Learn the many yoga therapy benefits, including pain and stress relief.",
            "image": {
              "url": null,
              "caption": null,
              "owner": null,
              "alt": null,
              "width": null,
              "height": null,
              "id": null,
              "fileName": null,
              "objectPath": null,
              "objectId": null,
              "empty": true,
              "notEmpty": false
            }
          },
          "metaData": null,
          "shortHeading": "Yoga and Tech",
          "viewType": null,
          "thumbImage": null,
          "contentLength": 0,
          "characterCount": 0,
          "review": false,
          "inNetworkCategoryLinks": [],
          "offNetworkCategoryLinks": [],
          "images": [],
          "subheading": null,
          "primaryImage": {
            "url": null,
            "caption": null,
            "owner": null,
            "alt": null,
            "width": null,
            "height": null,
            "id": null,
            "fileName": null,
            "objectPath": null,
            "objectId": null,
            "empty": true,
            "notEmpty": false
          },
          "bestTitle": "Understanding Yoga and Your Tech",
          "docId": 3993918
        },
        "children": {
          "limit": null,
          "offset": null,
          "totalSize": 0,
          "list": [],
          "empty": true
        },
        "descendantDocuments": []
      },
      {
        "docId": 3993917,
        "nodeType": "TAXONOMY",
        "primaryParent": null,
        "primaryParentWeight": 0.047215,
        "document": {
          "key": null,
          "revisionKey": null,
          "authorKey": null,
          "ownerKey": null,
          "url": "https://www.lifewire.com/yoga-audio-books-and-videos-3993917",
          "rootUrl": "https://www.lifewire.com/yoga-audio-books-and-videos-3993917",
          "templateType": "TAXONOMY",
          "documentState": null,
          "circulationsettings": null,
          "dates": null,
          "medicalBoardApproved": null,
          "editingAuthorKey": null,
          "noIndex": null,
          "title": "Yoga Video, Audio, and Book Reviews",
          "socialTitle": null,
          "keywords": {
            "limit": null,
            "offset": null,
            "totalSize": 0,
            "list": [],
            "empty": true
          },
          "metaDescription": null,
          "description": "Yoga is a great way to get exercise, improve balance and strengthen your body. Continue your practice at home with the best books, videos and apps.",
          "heading": "Yoga Video, Audio, and Book Reviews",
          "paging": null,
          "categoryPromos": {
            "limit": null,
            "offset": null,
            "totalSize": 0,
            "list": [],
            "empty": true
          },
          "category": null,
          "author": {
            "id": null,
            "type": null,
            "status": null,
            "siteDirName": null,
            "taxonomyInfo": null,
            "displayName": null,
            "displayNamePossessive": null,
            "contributingWriter": false,
            "language": null,
            "promotionDate": null,
            "liveDate": null,
            "terminationDate": null,
            "numberOfExperts": null,
            "socialPresence": [],
            "socialPresenceMap": {},
            "bioUrl": null,
            "imageUrl": null
          },
          "stamp": {
            "url": "https://www.lifewire.com/yoga-audio-books-and-videos-3993917",
            "stampValue": "vw_yoga-audio-books-and-videos",
            "adValue": "pidvw_yoga-audio-books-and-videos",
            "audit": {
              "clientId": null,
              "lastModified": null
            }
          },
          "userReview": null,
          "summary": {
            "title": "Yoga Video, Audio, and Book Reviews",
            "socialTitle": "Yoga Video, Audio, and Book Reviews",
            "heading": "Yoga Video, Audio, and Book Reviews",
            "description": "Yoga is a great way to get exercise, improve balance and strengthen your body. Continue your practice at home with the best books, videos and apps.",
            "image": {
              "url": null,
              "caption": null,
              "owner": null,
              "alt": null,
              "width": null,
              "height": null,
              "id": null,
              "fileName": null,
              "objectPath": null,
              "objectId": null,
              "empty": true,
              "notEmpty": false
            }
          },
          "metaData": null,
          "shortHeading": "Yoga Audio Books and Videos",
          "viewType": null,
          "thumbImage": null,
          "contentLength": 0,
          "characterCount": 0,
          "review": false,
          "inNetworkCategoryLinks": [],
          "offNetworkCategoryLinks": [],
          "images": [],
          "subheading": null,
          "primaryImage": {
            "url": null,
            "caption": null,
            "owner": null,
            "alt": null,
            "width": null,
            "height": null,
            "id": null,
            "fileName": null,
            "objectPath": null,
            "objectId": null,
            "empty": true,
            "notEmpty": false
          },
          "bestTitle": "Yoga Video, Audio, and Book Reviews",
          "docId": 3993917
        },
        "children": {
          "limit": null,
          "offset": null,
          "totalSize": 0,
          "list": [],
          "empty": true
        },
        "descendantDocuments": []
      },
      {
        "docId": 3993916,
        "nodeType": "TAXONOMY",
        "primaryParent": null,
        "primaryParentWeight": 0.046265,
        "document": {
          "key": null,
          "revisionKey": null,
          "authorKey": null,
          "ownerKey": null,
          "url": "https://www.lifewire.com/yoga-frequently-asked-questions-3993916",
          "rootUrl": "https://www.lifewire.com/yoga-frequently-asked-questions-3993916",
          "templateType": "TAXONOMY",
          "documentState": null,
          "circulationsettings": null,
          "dates": null,
          "medicalBoardApproved": null,
          "editingAuthorKey": null,
          "noIndex": null,
          "title": "Yoga Frequently Asked Questions",
          "socialTitle": null,
          "keywords": {
            "limit": null,
            "offset": null,
            "totalSize": 0,
            "list": [],
            "empty": true
          },
          "metaDescription": null,
          "description": "This yoga FAQ index answers all of your questions, including how to start an at-home practice, what to eat before and after a session, and more.",
          "heading": "Yoga Frequently Asked Questions",
          "paging": null,
          "categoryPromos": {
            "limit": null,
            "offset": null,
            "totalSize": 0,
            "list": [],
            "empty": true
          },
          "category": null,
          "author": {
            "id": null,
            "type": null,
            "status": null,
            "siteDirName": null,
            "taxonomyInfo": null,
            "displayName": null,
            "displayNamePossessive": null,
            "contributingWriter": false,
            "language": null,
            "promotionDate": null,
            "liveDate": null,
            "terminationDate": null,
            "numberOfExperts": null,
            "socialPresence": [],
            "socialPresenceMap": {},
            "bioUrl": null,
            "imageUrl": null
          },
          "stamp": {
            "url": "https://www.lifewire.com/yoga-frequently-asked-questions-3993916",
            "stampValue": "vw_yoga-frequently-asked-questions",
            "adValue": "pidvw_yoga-frequently-asked-questions",
            "audit": {
              "clientId": null,
              "lastModified": null
            }
          },
          "userReview": null,
          "summary": {
            "title": "Yoga Frequently Asked Questions",
            "socialTitle": "Yoga Frequently Asked Questions",
            "heading": "Yoga Frequently Asked Questions",
            "description": "This yoga FAQ index answers all of your questions, including how to start an at-home practice, what to eat before and after a session, and more.",
            "image": {
              "url": null,
              "caption": null,
              "owner": null,
              "alt": null,
              "width": null,
              "height": null,
              "id": null,
              "fileName": null,
              "objectPath": null,
              "objectId": null,
              "empty": true,
              "notEmpty": false
            }
          },
          "metaData": null,
          "shortHeading": "Frequently Asked Questions",
          "viewType": null,
          "thumbImage": null,
          "contentLength": 0,
          "characterCount": 0,
          "review": false,
          "inNetworkCategoryLinks": [],
          "offNetworkCategoryLinks": [],
          "images": [],
          "subheading": null,
          "primaryImage": {
            "url": null,
            "caption": null,
            "owner": null,
            "alt": null,
            "width": null,
            "height": null,
            "id": null,
            "fileName": null,
            "objectPath": null,
            "objectId": null,
            "empty": true,
            "notEmpty": false
          },
          "bestTitle": "Yoga Frequently Asked Questions",
          "docId": 3993916
        },
        "children": {
          "limit": null,
          "offset": null,
          "totalSize": 0,
          "list": [],
          "empty": true
        },
        "descendantDocuments": []
      },
      {
        "docId": 3993921,
        "nodeType": "TAXONOMY",
        "primaryParent": null,
        "primaryParentWeight": 0.046105,
        "document": {
          "key": null,
          "revisionKey": null,
          "authorKey": null,
          "ownerKey": null,
          "url": "https://www.lifewire.com/pregnancy-yoga-3993921",
          "rootUrl": "https://www.lifewire.com/pregnancy-yoga-3993921",
          "templateType": "TAXONOMY",
          "documentState": null,
          "circulationsettings": null,
          "dates": null,
          "medicalBoardApproved": null,
          "editingAuthorKey": null,
          "noIndex": null,
          "title": "Basics of Yoga During Pregnancy",
          "socialTitle": null,
          "keywords": {
            "limit": null,
            "offset": null,
            "totalSize": 0,
            "list": [],
            "empty": true
          },
          "metaDescription": null,
          "description": "Prenatal yoga is a great way to get exercise, but take caution. These pregnancy yoga poses will help you connect with your baby and prepare for childbirth.",
          "heading": "Basics of Yoga During Pregnancy",
          "paging": null,
          "categoryPromos": {
            "limit": null,
            "offset": null,
            "totalSize": 0,
            "list": [],
            "empty": true
          },
          "category": null,
          "author": {
            "id": null,
            "type": null,
            "status": null,
            "siteDirName": null,
            "taxonomyInfo": null,
            "displayName": null,
            "displayNamePossessive": null,
            "contributingWriter": false,
            "language": null,
            "promotionDate": null,
            "liveDate": null,
            "terminationDate": null,
            "numberOfExperts": null,
            "socialPresence": [],
            "socialPresenceMap": {},
            "bioUrl": null,
            "imageUrl": null
          },
          "stamp": {
            "url": "https://www.lifewire.com/pregnancy-yoga-3993921",
            "stampValue": "vw_pregnancy-yoga",
            "adValue": "pidvw_pregnancy-yoga",
            "audit": {
              "clientId": null,
              "lastModified": null
            }
          },
          "userReview": null,
          "summary": {
            "title": "Basics of Yoga During Pregnancy",
            "socialTitle": "Basics of Yoga During Pregnancy",
            "heading": "Basics of Yoga During Pregnancy",
            "description": "Prenatal yoga is a great way to get exercise, but take caution. These pregnancy yoga poses will help you connect with your baby and prepare for childbirth.",
            "image": {
              "url": null,
              "caption": null,
              "owner": null,
              "alt": null,
              "width": null,
              "height": null,
              "id": null,
              "fileName": null,
              "objectPath": null,
              "objectId": null,
              "empty": true,
              "notEmpty": false
            }
          },
          "metaData": null,
          "shortHeading": "Practicing Yoga During Pregnancy",
          "viewType": null,
          "thumbImage": null,
          "contentLength": 0,
          "characterCount": 0,
          "review": false,
          "inNetworkCategoryLinks": [],
          "offNetworkCategoryLinks": [],
          "images": [],
          "subheading": null,
          "primaryImage": {
            "url": null,
            "caption": null,
            "owner": null,
            "alt": null,
            "width": null,
            "height": null,
            "id": null,
            "fileName": null,
            "objectPath": null,
            "objectId": null,
            "empty": true,
            "notEmpty": false
          },
          "bestTitle": "Basics of Yoga During Pregnancy",
          "docId": 3993921
        },
        "children": {
          "limit": null,
          "offset": null,
          "totalSize": 0,
          "list": [],
          "empty": true
        },
        "descendantDocuments": []
      },
      {
        "docId": 3993922,
        "nodeType": "TAXONOMY",
        "primaryParent": null,
        "primaryParentWeight": 0.046045,
        "document": {
          "key": null,
          "revisionKey": null,
          "authorKey": null,
          "ownerKey": null,
          "url": "https://www.lifewire.com/advanced-yoga-3993922",
          "rootUrl": "https://www.lifewire.com/advanced-yoga-3993922",
          "templateType": "TAXONOMY",
          "documentState": null,
          "circulationsettings": null,
          "dates": null,
          "medicalBoardApproved": null,
          "editingAuthorKey": null,
          "noIndex": null,
          "title": "The Basics of Advanced Yoga",
          "socialTitle": null,
          "keywords": {
            "limit": null,
            "offset": null,
            "totalSize": 0,
            "list": [],
            "empty": true
          },
          "metaDescription": null,
          "description": "You've mastered the basics and are ready to take your yoga practice to the next level! Discover advanced postures and explore what it takes teach it.",
          "heading": "The Basics of Advanced Yoga",
          "paging": null,
          "categoryPromos": {
            "limit": null,
            "offset": null,
            "totalSize": 0,
            "list": [],
            "empty": true
          },
          "category": null,
          "author": {
            "id": null,
            "type": null,
            "status": null,
            "siteDirName": null,
            "taxonomyInfo": null,
            "displayName": null,
            "displayNamePossessive": null,
            "contributingWriter": false,
            "language": null,
            "promotionDate": null,
            "liveDate": null,
            "terminationDate": null,
            "numberOfExperts": null,
            "socialPresence": [],
            "socialPresenceMap": {},
            "bioUrl": null,
            "imageUrl": null
          },
          "stamp": {
            "url": "https://www.lifewire.com/advanced-yoga-3993922",
            "stampValue": "vw_advanced-yoga",
            "adValue": "pidvw_advanced-yoga",
            "audit": {
              "clientId": null,
              "lastModified": null
            }
          },
          "userReview": null,
          "summary": {
            "title": "The Basics of Advanced Yoga",
            "socialTitle": "The Basics of Advanced Yoga",
            "heading": "The Basics of Advanced Yoga",
            "description": "You've mastered the basics and are ready to take your yoga practice to the next level! Discover advanced postures and explore what it takes teach it.",
            "image": {
              "url": null,
              "caption": null,
              "owner": null,
              "alt": null,
              "width": null,
              "height": null,
              "id": null,
              "fileName": null,
              "objectPath": null,
              "objectId": null,
              "empty": true,
              "notEmpty": false
            }
          },
          "metaData": null,
          "shortHeading": "Advanced Yoga",
          "viewType": null,
          "thumbImage": null,
          "contentLength": 0,
          "characterCount": 0,
          "review": false,
          "inNetworkCategoryLinks": [],
          "offNetworkCategoryLinks": [],
          "images": [],
          "subheading": null,
          "primaryImage": {
            "url": null,
            "caption": null,
            "owner": null,
            "alt": null,
            "width": null,
            "height": null,
            "id": null,
            "fileName": null,
            "objectPath": null,
            "objectId": null,
            "empty": true,
            "notEmpty": false
          },
          "bestTitle": "The Basics of Advanced Yoga",
          "docId": 3993922
        },
        "children": {
          "limit": null,
          "offset": null,
          "totalSize": 0,
          "list": [],
          "empty": true
        },
        "descendantDocuments": []
      },
      {
        "docId": 3993924,
        "nodeType": "TAXONOMY",
        "primaryParent": null,
        "primaryParentWeight": 0.045345,
        "document": {
          "key": null,
          "revisionKey": null,
          "authorKey": null,
          "ownerKey": null,
          "url": "https://www.lifewire.com/yoga-advice-column-3993924",
          "rootUrl": "https://www.lifewire.com/yoga-advice-column-3993924",
          "templateType": "TAXONOMY",
          "documentState": null,
          "circulationsettings": null,
          "dates": null,
          "medicalBoardApproved": null,
          "editingAuthorKey": null,
          "noIndex": null,
          "title": "Ask Aunt Yoga Advice Column",
          "socialTitle": null,
          "keywords": {
            "limit": null,
            "offset": null,
            "totalSize": 0,
            "list": [],
            "empty": true
          },
          "metaDescription": null,
          "description": "Aunt Yoga will answer all your burning yoga questions, from asana advice to yoga etiquette, she covers it all. Discover how to maximize your practice.",
          "heading": "Ask Aunt Yoga Advice Column",
          "paging": null,
          "categoryPromos": {
            "limit": null,
            "offset": null,
            "totalSize": 0,
            "list": [],
            "empty": true
          },
          "category": null,
          "author": {
            "id": null,
            "type": null,
            "status": null,
            "siteDirName": null,
            "taxonomyInfo": null,
            "displayName": null,
            "displayNamePossessive": null,
            "contributingWriter": false,
            "language": null,
            "promotionDate": null,
            "liveDate": null,
            "terminationDate": null,
            "numberOfExperts": null,
            "socialPresence": [],
            "socialPresenceMap": {},
            "bioUrl": null,
            "imageUrl": null
          },
          "stamp": {
            "url": "https://www.lifewire.com/yoga-advice-column-3993924",
            "stampValue": "vw_yoga-advice-column",
            "adValue": "pidvw_yoga-advice-column",
            "audit": {
              "clientId": null,
              "lastModified": null
            }
          },
          "userReview": null,
          "summary": {
            "title": "Ask Aunt Yoga Advice Column",
            "socialTitle": "Ask Aunt Yoga Advice Column",
            "heading": "Ask Aunt Yoga Advice Column",
            "description": "Aunt Yoga will answer all your burning yoga questions, from asana advice to yoga etiquette, she covers it all. Discover how to maximize your practice.",
            "image": {
              "url": null,
              "caption": null,
              "owner": null,
              "alt": null,
              "width": null,
              "height": null,
              "id": null,
              "fileName": null,
              "objectPath": null,
              "objectId": null,
              "empty": true,
              "notEmpty": false
            }
          },
          "metaData": null,
          "shortHeading": "Yoga Advice Column",
          "viewType": null,
          "thumbImage": null,
          "contentLength": 0,
          "characterCount": 0,
          "review": false,
          "inNetworkCategoryLinks": [],
          "offNetworkCategoryLinks": [],
          "images": [],
          "subheading": null,
          "primaryImage": {
            "url": null,
            "caption": null,
            "owner": null,
            "alt": null,
            "width": null,
            "height": null,
            "id": null,
            "fileName": null,
            "objectPath": null,
            "objectId": null,
            "empty": true,
            "notEmpty": false
          },
          "bestTitle": "Ask Aunt Yoga Advice Column",
          "docId": 3993924
        },
        "children": {
          "limit": null,
          "offset": null,
          "totalSize": 0,
          "list": [],
          "empty": true
        },
        "descendantDocuments": []
      },
      {
        "docId": 3993925,
        "nodeType": "TAXONOMY",
        "primaryParent": null,
        "primaryParentWeight": 0.04509,
        "document": {
          "key": null,
          "revisionKey": null,
          "authorKey": null,
          "ownerKey": null,
          "url": "https://www.lifewire.com/yoga-poses-by-area-anatomical-focus-3993925",
          "rootUrl": "https://www.lifewire.com/yoga-poses-by-area-anatomical-focus-3993925",
          "templateType": "TAXONOMY",
          "documentState": null,
          "circulationsettings": null,
          "dates": null,
          "medicalBoardApproved": null,
          "editingAuthorKey": null,
          "noIndex": null,
          "title": "Yoga Poses by Area of Anatomical Focus",
          "socialTitle": null,
          "keywords": {
            "limit": null,
            "offset": null,
            "totalSize": 0,
            "list": [],
            "empty": true
          },
          "metaDescription": null,
          "description": "This yoga library will help you find the moves that work for you, whether you’re seeking yoga poses for focus, strength, stretching, stress relief and more.",
          "heading": "Yoga Poses by Area of Anatomical Focus",
          "paging": null,
          "categoryPromos": {
            "limit": null,
            "offset": null,
            "totalSize": 0,
            "list": [],
            "empty": true
          },
          "category": null,
          "author": {
            "id": null,
            "type": null,
            "status": null,
            "siteDirName": null,
            "taxonomyInfo": null,
            "displayName": null,
            "displayNamePossessive": null,
            "contributingWriter": false,
            "language": null,
            "promotionDate": null,
            "liveDate": null,
            "terminationDate": null,
            "numberOfExperts": null,
            "socialPresence": [],
            "socialPresenceMap": {},
            "bioUrl": null,
            "imageUrl": null
          },
          "stamp": {
            "url": "https://www.lifewire.com/yoga-poses-by-area-anatomical-focus-3993925",
            "stampValue": "vw_yoga-poses-by-area-anatomical-focus",
            "adValue": "pidvw_yoga-poses-by-area-anatomical-focus",
            "audit": {
              "clientId": null,
              "lastModified": null
            }
          },
          "userReview": null,
          "summary": {
            "title": "Yoga Poses by Area of Anatomical Focus",
            "socialTitle": "Yoga Poses by Area of Anatomical Focus",
            "heading": "Yoga Poses by Area of Anatomical Focus",
            "description": "This yoga library will help you find the moves that work for you, whether you’re seeking yoga poses for focus, strength, stretching, stress relief and more.",
            "image": {
              "url": null,
              "caption": null,
              "owner": null,
              "alt": null,
              "width": null,
              "height": null,
              "id": null,
              "fileName": null,
              "objectPath": null,
              "objectId": null,
              "empty": true,
              "notEmpty": false
            }
          },
          "metaData": null,
          "shortHeading": "Yoga Poses by Anatomical Focus",
          "viewType": null,
          "thumbImage": null,
          "contentLength": 0,
          "characterCount": 0,
          "review": false,
          "inNetworkCategoryLinks": [],
          "offNetworkCategoryLinks": [],
          "images": [],
          "subheading": null,
          "primaryImage": {
            "url": null,
            "caption": null,
            "owner": null,
            "alt": null,
            "width": null,
            "height": null,
            "id": null,
            "fileName": null,
            "objectPath": null,
            "objectId": null,
            "empty": true,
            "notEmpty": false
          },
          "bestTitle": "Yoga Poses by Area of Anatomical Focus",
          "docId": 3993925
        },
        "children": {
          "limit": null,
          "offset": null,
          "totalSize": 0,
          "list": [],
          "empty": true
        },
        "descendantDocuments": []
      },
      {
        "docId": 3993926,
        "nodeType": "TAXONOMY",
        "primaryParent": null,
        "primaryParentWeight": 0.04469,
        "document": {
          "key": null,
          "revisionKey": null,
          "authorKey": null,
          "ownerKey": null,
          "url": "https://www.lifewire.com/yoga-lifestyle-3993926",
          "rootUrl": "https://www.lifewire.com/yoga-lifestyle-3993926",
          "templateType": "TAXONOMY",
          "documentState": null,
          "circulationsettings": null,
          "dates": null,
          "medicalBoardApproved": null,
          "editingAuthorKey": null,
          "noIndex": null,
          "title": "The Lifestyle of a Yoga Student",
          "socialTitle": null,
          "keywords": {
            "limit": null,
            "offset": null,
            "totalSize": 0,
            "list": [],
            "empty": true
          },
          "metaDescription": null,
          "description": "When you are a dedicated yoga student, you may find your practice influencing other aspects of your life. Learn how to bring yoga into your daily routine.",
          "heading": "The Lifestyle of a Yoga Student",
          "paging": null,
          "categoryPromos": {
            "limit": null,
            "offset": null,
            "totalSize": 0,
            "list": [],
            "empty": true
          },
          "category": null,
          "author": {
            "id": null,
            "type": null,
            "status": null,
            "siteDirName": null,
            "taxonomyInfo": null,
            "displayName": null,
            "displayNamePossessive": null,
            "contributingWriter": false,
            "language": null,
            "promotionDate": null,
            "liveDate": null,
            "terminationDate": null,
            "numberOfExperts": null,
            "socialPresence": [],
            "socialPresenceMap": {},
            "bioUrl": null,
            "imageUrl": null
          },
          "stamp": {
            "url": "https://www.lifewire.com/yoga-lifestyle-3993926",
            "stampValue": "vw_yoga-lifestyle",
            "adValue": "pidvw_yoga-lifestyle",
            "audit": {
              "clientId": null,
              "lastModified": null
            }
          },
          "userReview": null,
          "summary": {
            "title": "The Lifestyle of a Yoga Student",
            "socialTitle": "The Lifestyle of a Yoga Student",
            "heading": "The Lifestyle of a Yoga Student",
            "description": "When you are a dedicated yoga student, you may find your practice influencing other aspects of your life. Learn how to bring yoga into your daily routine.",
            "image": {
              "url": null,
              "caption": null,
              "owner": null,
              "alt": null,
              "width": null,
              "height": null,
              "id": null,
              "fileName": null,
              "objectPath": null,
              "objectId": null,
              "empty": true,
              "notEmpty": false
            }
          },
          "metaData": null,
          "shortHeading": "Lifestyle",
          "viewType": null,
          "thumbImage": null,
          "contentLength": 0,
          "characterCount": 0,
          "review": false,
          "inNetworkCategoryLinks": [],
          "offNetworkCategoryLinks": [],
          "images": [],
          "subheading": null,
          "primaryImage": {
            "url": null,
            "caption": null,
            "owner": null,
            "alt": null,
            "width": null,
            "height": null,
            "id": null,
            "fileName": null,
            "objectPath": null,
            "objectId": null,
            "empty": true,
            "notEmpty": false
          },
          "bestTitle": "The Lifestyle of a Yoga Student",
          "docId": 3993926
        },
        "children": {
          "limit": null,
          "offset": null,
          "totalSize": 0,
          "list": [],
          "empty": true
        },
        "descendantDocuments": []
      },
      {
        "docId": 3993928,
        "nodeType": "TAXONOMY",
        "primaryParent": null,
        "primaryParentWeight": 0.044345,
        "document": {
          "key": null,
          "revisionKey": null,
          "authorKey": null,
          "ownerKey": null,
          "url": "https://www.lifewire.com/yoga-breathing-exercises-pranayama-3993928",
          "rootUrl": "https://www.lifewire.com/yoga-breathing-exercises-pranayama-3993928",
          "templateType": "TAXONOMY",
          "documentState": null,
          "circulationsettings": null,
          "dates": null,
          "medicalBoardApproved": null,
          "editingAuthorKey": null,
          "noIndex": null,
          "title": "Yoga Breathing Exercises - Pranayama",
          "socialTitle": null,
          "keywords": {
            "limit": null,
            "offset": null,
            "totalSize": 0,
            "list": [],
            "empty": true
          },
          "metaDescription": null,
          "description": "Breath control (pranayama) is an essential part of any yoga practice. Learn the basic types of yoga breathing exercises you’ll encounter during class.",
          "heading": "Yoga Breathing Exercises - Pranayama",
          "paging": null,
          "categoryPromos": {
            "limit": null,
            "offset": null,
            "totalSize": 0,
            "list": [],
            "empty": true
          },
          "category": null,
          "author": {
            "id": null,
            "type": null,
            "status": null,
            "siteDirName": null,
            "taxonomyInfo": null,
            "displayName": null,
            "displayNamePossessive": null,
            "contributingWriter": false,
            "language": null,
            "promotionDate": null,
            "liveDate": null,
            "terminationDate": null,
            "numberOfExperts": null,
            "socialPresence": [],
            "socialPresenceMap": {},
            "bioUrl": null,
            "imageUrl": null
          },
          "stamp": {
            "url": "https://www.lifewire.com/yoga-breathing-exercises-pranayama-3993928",
            "stampValue": "vw_yoga-breathing-exercises-pranayama",
            "adValue": "pidvw_yoga-breathing-exercises-pranayama",
            "audit": {
              "clientId": null,
              "lastModified": null
            }
          },
          "userReview": null,
          "summary": {
            "title": "Yoga Breathing Exercises - Pranayama",
            "socialTitle": "Yoga Breathing Exercises - Pranayama",
            "heading": "Yoga Breathing Exercises - Pranayama",
            "description": "Breath control (pranayama) is an essential part of any yoga practice. Learn the basic types of yoga breathing exercises you’ll encounter during class.",
            "image": {
              "url": null,
              "caption": null,
              "owner": null,
              "alt": null,
              "width": null,
              "height": null,
              "id": null,
              "fileName": null,
              "objectPath": null,
              "objectId": null,
              "empty": true,
              "notEmpty": false
            }
          },
          "metaData": null,
          "shortHeading": "Pranayama Yoga Breathing",
          "viewType": null,
          "thumbImage": null,
          "contentLength": 0,
          "characterCount": 0,
          "review": false,
          "inNetworkCategoryLinks": [],
          "offNetworkCategoryLinks": [],
          "images": [],
          "subheading": null,
          "primaryImage": {
            "url": null,
            "caption": null,
            "owner": null,
            "alt": null,
            "width": null,
            "height": null,
            "id": null,
            "fileName": null,
            "objectPath": null,
            "objectId": null,
            "empty": true,
            "notEmpty": false
          },
          "bestTitle": "Yoga Breathing Exercises - Pranayama",
          "docId": 3993928
        },
        "children": {
          "limit": null,
          "offset": null,
          "totalSize": 0,
          "list": [],
          "empty": true
        },
        "descendantDocuments": []
      },
      {
        "docId": 3993920,
        "nodeType": "TAXONOMY",
        "primaryParent": null,
        "primaryParentWeight": 0.02,
        "document": {
          "key": null,
          "revisionKey": null,
          "authorKey": null,
          "ownerKey": null,
          "url": "https://www.lifewire.com/yoga-glossary-3993920",
          "rootUrl": "https://www.lifewire.com/yoga-glossary-3993920",
          "templateType": "TAXONOMY",
          "documentState": null,
          "circulationsettings": null,
          "dates": null,
          "medicalBoardApproved": null,
          "editingAuthorKey": null,
          "noIndex": null,
          "title": "Glossary of Common Yoga Terms",
          "socialTitle": null,
          "keywords": {
            "limit": null,
            "offset": null,
            "totalSize": 0,
            "list": [],
            "empty": true
          },
          "metaDescription": null,
          "description": "Learn how to speak yogi with this comprehensive glossary of common yoga vocabulary, including slang, Sanskrit translations and more.",
          "heading": "Glossary of Common Yoga Terms",
          "paging": null,
          "categoryPromos": {
            "limit": null,
            "offset": null,
            "totalSize": 0,
            "list": [],
            "empty": true
          },
          "category": null,
          "author": {
            "id": null,
            "type": null,
            "status": null,
            "siteDirName": null,
            "taxonomyInfo": null,
            "displayName": null,
            "displayNamePossessive": null,
            "contributingWriter": false,
            "language": null,
            "promotionDate": null,
            "liveDate": null,
            "terminationDate": null,
            "numberOfExperts": null,
            "socialPresence": [],
            "socialPresenceMap": {},
            "bioUrl": null,
            "imageUrl": null
          },
          "stamp": {
            "url": "https://www.lifewire.com/yoga-glossary-3993920",
            "stampValue": "vw_yoga-glossary",
            "adValue": "pidvw_yoga-glossary",
            "audit": {
              "clientId": null,
              "lastModified": null
            }
          },
          "userReview": null,
          "summary": {
            "title": "Glossary of Common Yoga Terms",
            "socialTitle": "Glossary of Common Yoga Terms",
            "heading": "Glossary of Common Yoga Terms",
            "description": "Learn how to speak yogi with this comprehensive glossary of common yoga vocabulary, including slang, Sanskrit translations and more.",
            "image": {
              "url": null,
              "caption": null,
              "owner": null,
              "alt": null,
              "width": null,
              "height": null,
              "id": null,
              "fileName": null,
              "objectPath": null,
              "objectId": null,
              "empty": true,
              "notEmpty": false
            }
          },
          "metaData": null,
          "shortHeading": "Glossary",
          "viewType": null,
          "thumbImage": null,
          "contentLength": 0,
          "characterCount": 0,
          "review": false,
          "inNetworkCategoryLinks": [],
          "offNetworkCategoryLinks": [],
          "images": [],
          "subheading": null,
          "primaryImage": {
            "url": null,
            "caption": null,
            "owner": null,
            "alt": null,
            "width": null,
            "height": null,
            "id": null,
            "fileName": null,
            "objectPath": null,
            "objectId": null,
            "empty": true,
            "notEmpty": false
          },
          "bestTitle": "Glossary of Common Yoga Terms",
          "docId": 3993920
        },
        "children": {
          "limit": null,
          "offset": null,
          "totalSize": 0,
          "list": [],
          "empty": true
        },
        "descendantDocuments": []
      }
    ],
    "empty": false
  },
  "descendantDocuments": []
}