{
	"id": "image.default.money",
	"name": "image.default.money",
	"displayName": "Money Default Images",
	"data": [
		{
			"url" : "http://0.tqn.com/d/default/money/0/108707992.jpg",
			"owner" : "a.collectionRF/Getty Images",
			"width" : "2122",
			"height" : "1415"
		}
		,
		{
			"url" : "http://0.tqn.com/d/default/money/0/119544584.jpg",
			"owner" : "Plattform/Getty Images",
			"width" : "2122",
			"height" : "1415"
		}
		,
		{
			"url" : "http://0.tqn.com/d/default/money/0/119546712.jpg",
			"owner" : "Plattform/Getty Images ",
			"width" : "2122",
			"height" : "1415"
		}
		,
		{
			"url" : "http://0.tqn.com/d/default/money/0/140831009.jpg",
			"owner" : "uniquely india/Getty Images",
			"width" : "2061",
			"height" : "1457"
		}
		,
		{
			"url" : "http://0.tqn.com/d/default/money/0/143382521.jpg",
			"owner" : "JGI/Tom Grill/Blend Images/Getty Images",
			"width" : "2124",
			"height" : "1413"
		}
		,
		{
			"url" : "http://0.tqn.com/d/default/money/0/147849350.jpg",
			"owner" : "AID/a.collectionRF/Getty Images",
			"width" : "2122",
			"height" : "1415"
		}
		,
		{
			"url" : "http://0.tqn.com/d/default/money/0/150972776.jpg",
			"owner" : "Tetra Images - Jessica Peterson/Brand X Pictures/Getty Images",
			"width" : "2001",
			"height" : "1501"
		}
		,
		{
			"url" : "http://0.tqn.com/d/default/money/0/157697155.jpg",
			"owner" : "Mike Clarke/E+/Getty Images",
			"width" : "2122",
			"height" : "1415"
		}
		,
		{
			"url" : "http://0.tqn.com/d/default/money/0/168580604.jpg",
			"owner" : "Nicolas McComber/Vetta/Getty Images",
			"width" : "2122",
			"height" : "1415"
		}
		,
		{
			"url" : "http://0.tqn.com/d/default/money/0/169969777.jpg",
			"owner" : "Juanmonino/E+/Getty Images",
			"width" : "2058",
			"height" : "1459"
		}
		,
		{
			"url" : "http://0.tqn.com/d/default/money/0/170882007.jpg",
			"owner" : "Mike Kemp/Blend Images/Getty Images",
			"width" : "2122",
			"height" : "1415"
		}
		,
		{
			"url" : "http://0.tqn.com/d/default/money/0/171626056.jpg",
			"owner" : "Tetra Images/Brand X Pictures/Getty Images",
			"width" : "2124",
			"height" : "1414"
		}
		,
		{
			"url" : "http://0.tqn.com/d/default/money/0/175138816.jpg",
			"owner" : "Hero Images/Getty Images",
			"width" : "2122",
			"height" : "1415"
		}
		,
		{
			"url" : "http://0.tqn.com/d/default/money/0/177255995.jpg",
			"owner" : "Eric Audras/ONOKY/Getty Images",
			"width" : "2124",
			"height" : "1414"
		}
		,
		{
			"url" : "http://0.tqn.com/d/default/money/0/182747619.jpg",
			"owner" : "Marcela Barsse/E+/Getty Images",
			"width" : "2122",
			"height" : "1415"
		}
		,
		{
			"url" : "http://0.tqn.com/d/default/money/0/463012809.jpg",
			"owner" : "Jetta Productions/Blend Images/Getty Images",
			"width" : "2122",
			"height" : "1415"
		}
		,
		{
			"url" : "http://0.tqn.com/d/default/money/0/468838069.jpg",
			"owner" : "Martin Barraud/Caiaimage/Getty Images",
			"width" : "2073",
			"height" : "1449"
		}
		,
		{
			"url" : "http://0.tqn.com/d/default/money/0/468961355.jpg",
			"owner" : "chinaface/E+/Getty Images",
			"width" : "2117",
			"height" : "1418"
		}
		,
		{
			"url" : "http://0.tqn.com/d/default/money/0/469868421.jpg",
			"owner" : "alvarez/Vetta/Getty Images",
			"width" : "2025",
			"height" : "1482"
		}
		,
		{
			"url" : "http://0.tqn.com/d/default/money/0/469868429.jpg",
			"owner" : "alvarez/Vetta/Getty Images",
			"width" : "2004",
			"height" : "1498"
		}
		,
		{
			"url" : "http://0.tqn.com/d/default/money/0/476803847.jpg",
			"owner" : "Ariel Skelley/Blend Images/Getty Images",
			"width" : "2041",
			"height" : "1472"
		}
		,
		{
			"url" : "http://0.tqn.com/d/default/money/0/482141079.jpg",
			"owner" : "Jose Luis Pelaez Inc/Blend Images/Getty Images",
			"width" : "2097",
			"height" : "1433"
		}
		,
		{
			"url" : "http://0.tqn.com/d/default/money/0/482142745.jpg",
			"owner" : "Granger Wootz/Blend Images/Getty Images",
			"width" : "2122",
			"height" : "1415"
		}
		,
		{
			"url" : "http://0.tqn.com/d/default/money/0/482183751.jpg",
			"owner" : "Cultura RM/Matelly/Collection Mix: Subjects/Getty Images",
			"width" : "2122",
			"height" : "1415"
		}
		,
		{
			"url" : "http://0.tqn.com/d/default/money/0/485208127.jpg",
			"owner" : "Hero Images/Getty Images",
			"width" : "2122",
			"height" : "1415"
		}
		,
		{
			"url" : "http://0.tqn.com/d/default/money/0/490637121.jpg",
			"owner" : "Hero Images/Getty Images",
			"width" : "2122",
			"height" : "1415"
		}
		,
		{
			"url" : "http://0.tqn.com/d/default/money/0/492644377.jpg",
			"owner" : "Tetra Images/Getty Images",
			"width" : "2124",
			"height" : "1413"
		}
		,
		{
			"url" : "http://0.tqn.com/d/default/money/0/78773767.jpg",
			"owner" : "Fuse/Getty Images",
			"width" : "2290",
			"height" : "1526"
		}
		,
		{
			"url" : "http://0.tqn.com/d/default/money/0/86500834.jpg",
			"owner" : "Jupiterimages/Stockbyte/Getty Images",
			"width" : "2122",
			"height" : "1415"
		}
		,
		{
			"url" : "http://0.tqn.com/d/default/money/0/97421359.jpg",
			"owner" : "Jose Luis Pelaez Inc/Blend Images/Getty Images",
			"width" : "2290",
			"height" : "1527"
		}
	]
}
